wormpose/__init__.py
wormpose/__main__.py
wormpose/version.py
wormpose/commands/__init__.py
wormpose/commands/calibrate_dataset.py
wormpose/commands/evaluate_model.py
wormpose/commands/export_results.py
wormpose/commands/generate_training_data.py
wormpose/commands/postprocess_results.py
wormpose/commands/predict_dataset.py
wormpose/commands/train_model.py
wormpose/commands/visualize_results.py
wormpose/commands/utils/__init__.py
wormpose/commands/utils/results_saver.py
wormpose/commands/utils/time_sampling.py
wormpose/config/__init__.py
wormpose/config/default_paths.py
wormpose/config/experiment_config.py
wormpose/dataset/__init__.py
wormpose/dataset/base_dataset.py
wormpose/dataset/features.py
wormpose/dataset/loader.py
wormpose/dataset/image_processing/__init__.py
wormpose/dataset/image_processing/frame_preprocessor.py
wormpose/dataset/image_processing/image_utils.py
wormpose/dataset/image_processing/options.py
wormpose/dataset/image_processing/simple_frame_preprocessing.py
wormpose/dataset/loaders/__init__.py
wormpose/dataset/loaders/hdf5features.py
wormpose/dataset/loaders/images_folder.py
wormpose/dataset/loaders/resizer.py
wormpose/dataset/loaders/sample_data.py
wormpose/dataset/loaders/tierpsy/__init__.py
wormpose/dataset/loaders/tierpsy/features_dataset.py
wormpose/dataset/loaders/tierpsy/frames_dataset.py
wormpose/dataset/loaders/tierpsy/results_exporter.py
wormpose/demo/__init__.py
wormpose/demo/real_simple_visualizer.py
wormpose/demo/synthetic_simple_visualizer.py
wormpose/images/__init__.py
wormpose/images/real_dataset.py
wormpose/images/worm_drawing.py
wormpose/images/scoring/__init__.py
wormpose/images/scoring/centerline_accuracy_check.py
wormpose/images/scoring/image_scoring.py
wormpose/images/scoring/results_scoring.py
wormpose/images/scoring/scoring_data_manager.py
wormpose/images/synthetic/__init__.py
wormpose/images/synthetic/_coord_transform.py
wormpose/images/synthetic/_helpers.py
wormpose/images/synthetic/synthetic_dataset.py
wormpose-1.3.0.dist-info/LICENSE
wormpose-1.3.0.dist-info/METADATA
wormpose-1.3.0.dist-info/WHEEL
wormpose-1.3.0.dist-info/entry_points.txt
wormpose-1.3.0.dist-info/top_level.txt
wormpose-1.3.0.dist-info/RECORD
