Metadata-Version: 2.1
Name: wormpose
Version: 1.3.0
Summary: WormPose: Image synthesis and convolutional networks for pose estimation in C. elegans
Home-page: https://iteal.github.io/wormpose/
Author: "Laetitia M Hebert, Antonio C Costa"
Author-email: laetitia.m.hebert@gmail.com
License: BSD 3-Clause License
Project-URL: Documentation, https://iteal.github.io/wormpose/documentation.html
Project-URL: Twitter, https://twitter.com/wormpose
Project-URL: GitHub, https://github.com/iteal/wormpose
Project-URL: Bug-Tracker, https://github.com/iteal/wormpose/issues
Keywords: animal pose estimation,c. elegans
Platform: UNKNOWN
Classifier: Development Status :: 4 - Beta
Classifier: Intended Audience :: Science/Research
Classifier: License :: OSI Approved :: BSD License
Classifier: Programming Language :: Python
Classifier: Programming Language :: Python :: 3
Classifier: Programming Language :: Python :: 3.6
Classifier: Programming Language :: Python :: 3.7
Classifier: Programming Language :: Python :: 3.8
Classifier: Operating System :: OS Independent
Classifier: Topic :: Scientific/Engineering :: Image Recognition
Requires-Python: >=3.6
Requires-Dist: opencv-python
Requires-Dist: tensorflow (>=2)
Requires-Dist: numpy
Requires-Dist: h5py
Requires-Dist: scipy
